chanjing/__init__.py
chanjing/core.py
chanjing/exceptions.py
chanjing/schemas.py
chanjing/synthesis.py
chanjing/user_info.py
chanjing/customised/audio.py
chanjing/customised/person.py
chanjing2-0.1.2.dist-info/METADATA
chanjing2-0.1.2.dist-info/WHEEL
chanjing2-0.1.2.dist-info/licenses/LICENSE
chanjing2-0.1.2.dist-info/RECORD
