Metadata-Version: 2.4
Name: chanjing2
Version: 0.1.2
Summary: 蝉镜数字人SDK
Project-URL: Homepage, https://github.com/yourusername/chanjing
Project-URL: Bug Tracker, https://github.com/yourusername/chanjing/issues
Author-email: AiWorld Developer <dev@example.com>
License: MIT
License-File: LICENSE
Classifier: License :: OSI Approved :: MIT License
Classifier: Operating System :: OS Independent
Classifier: Programming Language :: Python :: 3
Requires-Python: >=3.12
Requires-Dist: curlify2>=2.0.0
Requires-Dist: pydantic>=2.10.6
Requires-Dist: requests>=2.32.3
Provides-Extra: dev
Requires-Dist: pytest>=6.0; extra == 'dev'
Requires-Dist: ruff>=0.0.254; extra == 'dev'
